intentclassification/__init__.py
intentclassification/intentclassification.py
intentclassification-0.1.1.dist-info/METADATA
intentclassification-0.1.1.dist-info/WHEEL
intentclassification-0.1.1.dist-info/top_level.txt
intentclassification-0.1.1.dist-info/RECORD
