Metadata-Version: 2.1
Name: intentclassification
Version: 0.1.1
Summary: Intentclassification AI in python, easy to use intentclassifier package.
Author: zhiftyDK
Author-email: juulstausholmoscar@gmail.com
License: The Unlicense
Project-URL: Source, https://github.com/zhiftyDK/intentclassification
Classifier: Development Status :: 3 - Alpha
Classifier: Intended Audience :: Developers
Classifier: Programming Language :: Python :: 3
Requires-Dist: nltk
Requires-Dist: numpy
Requires-Dist: tensorflow
